[
	{ "coordinates": { "x": 0, "y": 0, "z": 0 }, "type": "pack" },
	{ "coordinates": { "x": 1, "y": 0, "z": 0 }, "type": "soil" },
	{ "coordinates": { "x": 0, "y": 1, "z": 0 }, "type": "soil" },
	{ "coordinates": { "x": 0, "y": 0, "z": 1 }, "type": "soil" },
	{ "coordinates": { "x": -1, "y": 0, "z": 0 }, "type": "soil" },
	{ "coordinates": { "x": 0, "y": -1, "z": 0 }, "type": "soil" },
	{ "coordinates": { "x": 0, "y": 0, "z": -1 }, "type": "soil" },

	{ "coordinates": { "x": 2, "y": 0, "z": 0 }, "type": "pack" },
	{ "coordinates": { "x": 0, "y": 2, "z": 0 }, "type": "pack" },
	{ "coordinates": { "x": 0, "y": 0, "z": 2 }, "type": "pack" },
	{ "coordinates": { "x": -2, "y": 0, "z": 0 }, "type": "pack" },
	{ "coordinates": { "x": 0, "y": -2, "z": 0 }, "type": "pack" },
	{ "coordinates": { "x": 0, "y": 0, "z": -2 }, "type": "pack" },
	{ "coordinates": { "x": 1, "y": 1, "z": 0 }, "type": "pack" },
	{ "coordinates": { "x": -1, "y": -1, "z": 0 }, "type": "pack" },
	{ "coordinates": { "x": 1, "y": 0, "z": -1 }, "type": "pack" },
	{ "coordinates": { "x": 0, "y": -1, "z": -1 }, "type": "pack" },
	{ "coordinates": { "x": -1, "y": 0, "z": 1 }, "type": "pack" },
	{ "coordinates": { "x": 0, "y": 1, "z": 1 }, "type": "pack" },
	{ "coordinates": { "x": 3, "y": 0, "z": 0 }, "type": "pack" },
	{ "coordinates": { "x": 0, "y": 3, "z": 0 }, "type": "pack" },
	{ "coordinates": { "x": 0, "y": 0, "z": 3 }, "type": "pack" },
	{ "coordinates": { "x": -3, "y": 0, "z": 0 }, "type": "pack" },
	{ "coordinates": { "x": 0, "y": -3, "z": 0 }, "type": "pack" },
	{ "coordinates": { "x": 0, "y": 0, "z": -3 }, "type": "pack" },
	{ "coordinates": { "x": 4, "y": 0, "z": 0 }, "type": "pack" },
	{ "coordinates": { "x": 0, "y": 4, "z": 0 }, "type": "pack" },
	{ "coordinates": { "x": 0, "y": 0, "z": 4 }, "type": "pack" },
	{ "coordinates": { "x": -4, "y": 0, "z": 0 }, "type": "pack" },
	{ "coordinates": { "x": 0, "y": -4, "z": 0 }, "type": "pack" },
	{ "coordinates": { "x": 0, "y": 0, "z": -4 }, "type": "pack" },
	{ "coordinates": { "x": 4, "y": 1, "z": 0 }, "type": "pack" },
	{ "coordinates": { "x": 4, "y": 0, "z": -1 }, "type": "pack" },
	{ "coordinates": { "x": 1, "y": 4, "z": 0 }, "type": "pack" },
	{ "coordinates": { "x": 0, "y": 4, "z": 1 }, "type": "pack" },
	{ "coordinates": { "x": 0, "y": 1, "z": 4 }, "type": "pack" },
	{ "coordinates": { "x": -1, "y": 0, "z": 4 }, "type": "pack" },
	{ "coordinates": { "x": -4, "y": -1, "z": 0 }, "type": "pack" },
	{ "coordinates": { "x": -4, "y": 0, "z": 1 }, "type": "pack" },
	{ "coordinates": { "x": -1, "y": -4, "z": 0 }, "type": "pack" },
	{ "coordinates": { "x": 0, "y": -4, "z": -1 }, "type": "pack" },
	{ "coordinates": { "x": 1, "y": 0, "z": -4 }, "type": "pack" },
	{ "coordinates": { "x": 0, "y": -1, "z": -4 }, "type": "pack" },

	{ "coordinates": { "x": 0, "y": 2, "z": 2 }, "type": "soil" },
	{ "coordinates": { "x": 1, "y": 2, "z": 2 }, "type": "soil" },
	{ "coordinates": { "x": 0, "y": 3, "z": 2 }, "type": "soil" },
	{ "coordinates": { "x": 0, "y": 2, "z": 3 }, "type": "soil" },
	{ "coordinates": { "x": -1, "y": 2, "z": 2 }, "type": "soil" },
	{ "coordinates": { "x": 0, "y": 1, "z": 2 }, "type": "soil" },
	{ "coordinates": { "x": 0, "y": 2, "z": 1 }, "type": "soil" },

	{ "coordinates": { "x": 2, "y": 2, "z": 0 }, "type": "soil" },
	{ "coordinates": { "x": 3, "y": 2, "z": 0 }, "type": "soil" },
	{ "coordinates": { "x": 2, "y": 3, "z": 0 }, "type": "soil" },
	{ "coordinates": { "x": 2, "y": 2, "z": 1 }, "type": "soil" },
	{ "coordinates": { "x": 1, "y": 2, "z": 0 }, "type": "soil" },
	{ "coordinates": { "x": 2, "y": 1, "z": 0 }, "type": "soil" },
	{ "coordinates": { "x": 2, "y": 2, "z": -1 }, "type": "soil" },

	{ "coordinates": { "x": 2, "y": 0, "z": -2 }, "type": "soil" },
	{ "coordinates": { "x": 3, "y": 0, "z": -2 }, "type": "soil" },
	{ "coordinates": { "x": 2, "y": 1, "z": -2 }, "type": "soil" },
	{ "coordinates": { "x": 2, "y": 0, "z": -1 }, "type": "soil" },
	{ "coordinates": { "x": 1, "y": 0, "z": -2 }, "type": "soil" },
	{ "coordinates": { "x": 2, "y": -1, "z": -2 }, "type": "soil" },
	{ "coordinates": { "x": 2, "y": 0, "z": -3 }, "type": "soil" },

	{ "coordinates": { "x": 0, "y": -2, "z": -2 }, "type": "soil" },
	{ "coordinates": { "x": 1, "y": -2, "z": -2 }, "type": "soil" },
	{ "coordinates": { "x": 0, "y": -1, "z": -2 }, "type": "soil" },
	{ "coordinates": { "x": 0, "y": -2, "z": -1 }, "type": "soil" },
	{ "coordinates": { "x": -1, "y": -2, "z": -2 }, "type": "soil" },
	{ "coordinates": { "x": 0, "y": -3, "z": -2 }, "type": "soil" },
	{ "coordinates": { "x": 0, "y": -2, "z": -3 }, "type": "soil" },

	{ "coordinates": { "x": -2, "y": -2, "z": 0 }, "type": "soil" },
	{ "coordinates": { "x": -1, "y": -2, "z": 0 }, "type": "soil" },
	{ "coordinates": { "x": -2, "y": -1, "z": 0 }, "type": "soil" },
	{ "coordinates": { "x": -2, "y": -2, "z": 1 }, "type": "soil" },
	{ "coordinates": { "x": -3, "y": -2, "z": 0 }, "type": "soil" },
	{ "coordinates": { "x": -2, "y": -3, "z": 0 }, "type": "soil" },
	{ "coordinates": { "x": -2, "y": -2, "z": -1 }, "type": "soil" },

	{ "coordinates": { "x": -2, "y": 0, "z": 2 }, "type": "soil" },
	{ "coordinates": { "x": -1, "y": 0, "z": 2 }, "type": "soil" },
	{ "coordinates": { "x": -2, "y": 1, "z": 2 }, "type": "soil" },
	{ "coordinates": { "x": -2, "y": 0, "z": 3 }, "type": "soil" },
	{ "coordinates": { "x": -3, "y": 0, "z": 2 }, "type": "soil" },
	{ "coordinates": { "x": -2, "y": -1, "z": 2 }, "type": "soil" },
	{ "coordinates": { "x": -2, "y": 0, "z": 1 }, "type": "soil" },

	{ "coordinates": { "x": 6, "y": 0, "z": 0 }, "type": "soil" },
	{ "coordinates": { "x": 7, "y": 0, "z": 0 }, "type": "spore", "team": "Player 1" },
	{ "coordinates": { "x": 6, "y": 1, "z": 0 }, "type": "soil" },
	{ "coordinates": { "x": 6, "y": 0, "z": 1 }, "type": "soil" },
	{ "coordinates": { "x": 5, "y": 0, "z": 0 }, "type": "soil" },
	{ "coordinates": { "x": 6, "y": -1, "z": 0 }, "type": "soil" },
	{ "coordinates": { "x": 6, "y": 0, "z": -1 }, "type": "soil" },

	{ "coordinates": { "x": -6, "y": 0, "z": 0 }, "type": "soil" },
	{ "coordinates": { "x": -7, "y": 0, "z": 0 }, "type": "spore", "team": "Player 2" },
	{ "coordinates": { "x": -6, "y": 1, "z": 0 }, "type": "soil" },
	{ "coordinates": { "x": -6, "y": 0, "z": 1 }, "type": "soil" },
	{ "coordinates": { "x": -5, "y": 0, "z": 0 }, "type": "soil" },
	{ "coordinates": { "x": -6, "y": -1, "z": 0 }, "type": "soil" },
	{ "coordinates": { "x": -6, "y": 0, "z": -1 }, "type": "soil" },

	{ "coordinates": { "x": 0, "y": 6, "z": 0 }, "type": "soil" },
	{ "coordinates": { "x": 1, "y": 6, "z": 0 }, "type": "soil" },
	{ "coordinates": { "x": 0, "y": 7, "z": 0 }, "type": "spore", "team": "Player 3" },
	{ "coordinates": { "x": 0, "y": 6, "z": 1 }, "type": "soil" },
	{ "coordinates": { "x": -1, "y": 6, "z": 0 }, "type": "soil" },
	{ "coordinates": { "x": 0, "y": 5, "z": 0 }, "type": "soil" },
	{ "coordinates": { "x": 0, "y": 6, "z": -1 }, "type": "soil" },

	{ "coordinates": { "x": 0, "y": -6, "z": 0 }, "type": "soil" },
	{ "coordinates": { "x": 1, "y": -6, "z": 0 }, "type": "soil" },
	{ "coordinates": { "x": 0, "y": -7, "z": 0 }, "type": "spore", "team": "Player 4" },
	{ "coordinates": { "x": 0, "y": -6, "z": 1 }, "type": "soil" },
	{ "coordinates": { "x": -1, "y": -6, "z": 0 }, "type": "soil" },
	{ "coordinates": { "x": 0, "y": -5, "z": 0 }, "type": "soil" },
	{ "coordinates": { "x": 0, "y": -6, "z": -1 }, "type": "soil" },

	{ "coordinates": { "x": 0, "y": 0, "z": 6 }, "type": "soil" },
	{ "coordinates": { "x": 1, "y": 0, "z": 6 }, "type": "soil" },
	{ "coordinates": { "x": 0, "y": 1, "z": 6 }, "type": "soil" },
	{ "coordinates": { "x": 0, "y": 0, "z": 7 }, "type": "spore", "team": "Player 5" },
	{ "coordinates": { "x": -1, "y": 0, "z": 6 }, "type": "soil" },
	{ "coordinates": { "x": 0, "y": -1, "z": 6 }, "type": "soil" },
	{ "coordinates": { "x": 0, "y": 0, "z": 5 }, "type": "soil" },

	{ "coordinates": { "x": 0, "y": 0, "z": -6 }, "type": "soil" },
	{ "coordinates": { "x": 1, "y": 0, "z": -6 }, "type": "soil" },
	{ "coordinates": { "x": 0, "y": 1, "z": -6 }, "type": "soil" },
	{ "coordinates": { "x": 0, "y": 0, "z": -7 }, "type": "spore", "team": "Player 6" },
	{ "coordinates": { "x": -1, "y": 0, "z": -6 }, "type": "soil" },
	{ "coordinates": { "x": 0, "y": -1, "z": -6 }, "type": "soil" },
	{ "coordinates": { "x": 0, "y": 0, "z": -5 }, "type": "soil" }
]
